LICENSE
MANIFEST.in
README.md
setup.py
terma/__init__.py
terma/app.py
terma/completer.py
terma/config.py
terma/prompt.py
terma/translator.py
terma/utils.py
terma.egg-info/PKG-INFO
terma.egg-info/SOURCES.txt
terma.egg-info/dependency_links.txt
terma.egg-info/entry_points.txt
terma.egg-info/requires.txt
terma.egg-info/top_level.txt