Metadata-Version: 2.1
Name: terma
Version: 1.0.3
Summary: Terminal Assistant
Author: Arjun Shenoy A V
Author-email: arjunshenoyav@gmail.com
License-File: LICENSE
